{
  "parent": "minecraft:recipes/root",
  "criteria": {
    "has_the_recipe": {
      "conditions": {
        "recipe": "techplusplus:iron_ingot_from_iron_block"
      },
      "trigger": "minecraft:recipe_unlocked"
    },
    "iron_block": {
      "conditions": {
        "items": [
          {
            "items": "minecraft:iron_block"
          }
        ]
      },
      "trigger": "minecraft:inventory_changed"
    }
  },
  "requirements": [
    [
      "has_the_recipe",
      "iron_block"
    ]
  ],
  "rewards": {
    "recipes": [
      "techplusplus:iron_ingot_from_iron_block"
    ]
  }
}